sunverse/__init__.py
sunverse/enums.py
sunverse/errors.py
sunverse/sunverse.py
sunverse/objects/__init__.py
sunverse/objects/artist.py
sunverse/objects/attachments.py
sunverse/objects/comment.py
sunverse/objects/community.py
sunverse/objects/live.py
sunverse/objects/media.py
sunverse/objects/member.py
sunverse/objects/moment.py
sunverse/objects/notice.py
sunverse/objects/notification.py
sunverse/objects/post.py
sunverse/utils/__init__.py
sunverse/utils/urls.py
sunverse/utils/utilities.py
Sun_Weverse-1.0.0.6.dist-info/LICENSE
Sun_Weverse-1.0.0.6.dist-info/METADATA
Sun_Weverse-1.0.0.6.dist-info/WHEEL
Sun_Weverse-1.0.0.6.dist-info/top_level.txt
Sun_Weverse-1.0.0.6.dist-info/RECORD
