Metadata-Version: 2.1
Name: Sun-Weverse
Version: 1.0.0.6
Summary: Sun Weverse seeks to provide developers with a tool that allows them to make a bot that is able to retrieve Weverse Posts in semi real-time with relative ease.
Home-page: https://github.com/Anson-Quek/Sun-Weverse
Author: Anson Quek
License: MIT
Classifier: Development Status :: 5 - Production/Stable
Classifier: License :: OSI Approved :: MIT License
Classifier: Intended Audience :: Developers
Classifier: Natural Language :: English
Classifier: Programming Language :: Python :: 3.10
Requires-Python: >=3.10
License-File: LICENSE
Requires-Dist: aiohttp
Requires-Dist: setuptools
